mt_events/__init__.py
mt_events-0.1.2.dist-info/licenses/LICENSE
mt_events-0.1.2.dist-info/METADATA
mt_events-0.1.2.dist-info/WHEEL
mt_events-0.1.2.dist-info/top_level.txt
mt_events-0.1.2.dist-info/RECORD
