Metadata-Version: 2.4
Name: mt_events
Version: 0.1.2
Summary: Utility module providing event queues and JS style async awaiter promises
Author: Illinois Plasma Institute
Author-email: Alp Doganer <doganer2@illinois.edu>
Maintainer-email: Alp Doganer <doganer2@illinois.edu>
License: Unlicense
Project-URL: Repository, https://github.com/IPI-EUVL/mt_events.git
Requires-Python: >=3.0
License-File: LICENSE
Dynamic: license-file
